NeSy4PPM/Evaluation.py
NeSy4PPM/__init__.py
NeSy4PPM/Data_preprocessing/__init__.py
NeSy4PPM/Data_preprocessing/data_preprocessing.py
NeSy4PPM/Data_preprocessing/log_utils.py
NeSy4PPM/Data_preprocessing/shared_variables.py
NeSy4PPM/Data_preprocessing/utils.py
NeSy4PPM/Prediction/Checkers.py
NeSy4PPM/Prediction/__init__.py
NeSy4PPM/Prediction/create_event_log.py
NeSy4PPM/Prediction/inference_algorithm.py
NeSy4PPM/Prediction/predict_suffix.py
NeSy4PPM/Prediction/prepare_data.py
NeSy4PPM/Prediction/__pycache__/Checkers.cpython-310.pyc
NeSy4PPM/Prediction/__pycache__/__init__.cpython-310.pyc
NeSy4PPM/Prediction/__pycache__/__init__.cpython-311.pyc
NeSy4PPM/Prediction/__pycache__/__init__.cpython-312.pyc
NeSy4PPM/Prediction/__pycache__/create_event_log.cpython-310.pyc
NeSy4PPM/Prediction/__pycache__/prepare_data.cpython-310.pyc
NeSy4PPM/ProbDeclmonitor/__init__.py
NeSy4PPM/ProbDeclmonitor/autUtils.py
NeSy4PPM/ProbDeclmonitor/ltlUtils.py
NeSy4PPM/ProbDeclmonitor/probDeclPredictor.py
NeSy4PPM/ProbDeclmonitor/__pycache__/__init__.cpython-310.pyc
NeSy4PPM/ProbDeclmonitor/__pycache__/autUtils.cpython-310.pyc
NeSy4PPM/ProbDeclmonitor/__pycache__/ltlUtils.cpython-310.pyc
NeSy4PPM/ProbDeclmonitor/__pycache__/probDeclPredictor.cpython-310.pyc
NeSy4PPM/Training/Modulator.py
NeSy4PPM/Training/__init__.py
NeSy4PPM/Training/train_common.py
NeSy4PPM/Training/train_model.py
NeSy4PPM/__pycache__/__init__.cpython-310.pyc
NeSy4PPM/__pycache__/__init__.cpython-311.pyc
NeSy4PPM/__pycache__/__init__.cpython-312.pyc
nesy4ppm-0.1.0.dist-info/METADATA
nesy4ppm-0.1.0.dist-info/WHEEL
nesy4ppm-0.1.0.dist-info/top_level.txt
nesy4ppm-0.1.0.dist-info/RECORD
