Metadata-Version: 2.4
Name: nesy4ppm
Version: 0.1.0
Summary: Python library to perform learning and suffix prediction with background knowledge under concept drifts.
Author-email: Jamila Oukharijane <jamila.oukharijane@unibz.it>, Ivan Donadello <ivan.donadello@unibz.it>, Fabrizio Maria Maggi <maggi@inf.unibz.it>
Project-URL: Homepage, https://github.com/JamilaOUKHARIJANE/NeSy4PPM
Keywords: python,process mining,predictive process monitoring,suffix prediction,background knowledge
Requires-Python: >=3.9.7
Requires-Dist: declare4py>=2.2.0
Requires-Dist: tensorflow==2.10.1
Requires-Dist: Distance==0.1.3
Requires-Dist: keras==2.10.0
Requires-Dist: keras-nlp==0.4.1
Requires-Dist: jellyfish==0.9.0
Requires-Dist: absl-py==2.3.0
